<?xml version="1.0" ?>
<!DOCTYPE PubmedArticleSet PUBLIC "-//NLM//DTD PubMedArticle, 1st January 2025//EN" "https://dtd.nlm.nih.gov/ncbi/pubmed/out/pubmed_250101.dtd">
<PubmedArticleSet>
<PubmedArticle><MedlineCitation Status="MEDLINE" Owner="NLM" IndexingMethod="Automated"><PMID Version="1">36726127</PMID><DateCompleted><Year>2023</Year><Month>02</Month><Day>03</Day></DateCompleted><DateRevised><Year>2024</Year><Month>09</Month><Day>12</Day></DateRevised><Article PubModel="Electronic"><Journal><ISSN IssnType="Electronic">1748-5908</ISSN><JournalIssue CitedMedium="Internet"><Volume>18</Volume><Issue>1</Issue><PubDate><Year>2023</Year><Month>Feb</Month><Day>01</Day></PubDate></JournalIssue><Title>Implementation science : IS</Title><ISOAbbreviation>Implement Sci</ISOAbbreviation></Journal><ArticleTitle>Study protocol for a factorial-randomized controlled trial evaluating the implementation, costs, effectiveness, and sustainment of digital therapeutics for substance use disorder in primary care (DIGITS Trial).</ArticleTitle><Pagination><StartPage>3</StartPage><MedlinePgn>3</MedlinePgn></Pagination><ELocationID EIdType="pii" ValidYN="Y">3</ELocationID><ELocationID EIdType="doi" ValidYN="Y">10.1186/s13012-022-01258-9</ELocationID><Abstract><AbstractText Label="BACKGROUND">Experts recommend that treatment for substance use disorder (SUD) be integrated into primary care. The Digital Therapeutics for Opioids and Other SUD (DIGITS) Trial tests strategies for implementing reSET&#xae; and reSET-O&#xae;, which are prescription digital therapeutics for SUD and opioid use disorder, respectively, that include the community reinforcement approach, contingency management, and fluency training to reinforce concept mastery. This purpose of this trial is to test whether two implementation strategies improve implementation success (Aim 1) and achieve better population-level cost effectiveness (Aim 2) over a standard implementation approach.</AbstractText><AbstractText Label="METHODS/DESIGN">The DIGITS Trial is a hybrid type III cluster-randomized trial. It examines outcomes of implementation strategies, rather than studying clinical outcomes of a digital therapeutic. It includes 22 primary care clinics from a healthcare system in Washington State and patients with unhealthy substance use who visit clinics during an active implementation period (up to one year). Primary care clinics implemented reSET and reSET-O using a multifaceted implementation strategy previously used by clinical leaders to roll-out smartphone apps ("standard implementation" including discrete strategies such as clinician training, electronic health record tools). Clinics were randomized as 21 sites in a 2x2 factorial design to receive up to two added implementation strategies: (1) practice facilitation, and/or (2) health coaching. Outcome data are derived from electronic health records and logs of digital therapeutic usage. Aim 1's primary outcomes include reach of the digital therapeutics to patients and fidelity of patients' use of the digital therapeutics to clinical recommendations. Substance use and engagement in SUD care are additional outcomes. In Aim 2, population-level cost effectiveness analysis will inform the economic benefit of the implementation strategies compared to standard implementation. Implementation is monitored using formative evaluation, and sustainment will be studied for up to one year using qualitative and quantitative research methods.</AbstractText><AbstractText Label="DISCUSSION">The DIGITS Trial uses an experimental design to test whether implementation strategies increase and improve the delivery of digital therapeutics for SUDs when embedded in a large healthcare system. It will provide data on the potential benefits and cost-effectiveness of alternative implementation strategies.</AbstractText><AbstractText Label="CLINICALTRIALS">gov Identifier: NCT05160233 (Submitted 12/3/2021). https://clinicaltrials.gov/ct2/show/NCT05160233.</AbstractText><CopyrightInformation>&#xa9; 2023. The Author(s).</CopyrightInformation></Abstract><AuthorList CompleteYN="Y"><Author ValidYN="Y"><LastName>Glass</LastName><ForeName>Joseph E</ForeName><Initials>JE</Initials><Identifier Source="ORCID">0000-0002-2923-3698</Identifier><AffiliationInfo><Affiliation>Kaiser Permanente Washington Health Research Institute, 1730 Minor Ave, Seattle, WA, 98101, USA. Joseph.E.Glass@kp.org.</Affiliation></AffiliationInfo></Author><Author ValidYN="Y"><LastName>Dorsey</LastName><ForeName>Caitlin N</ForeName><Initials>CN</Initials><AffiliationInfo><Affiliation>Kaiser Permanente Washington Health Research Institute, 1730 Minor Ave, Seattle, WA, 98101, USA.</Affiliation></AffiliationInfo></Author><Author ValidYN="Y"><LastName>Beatty</LastName><ForeName>Tara</ForeName><Initials>T</Initials><AffiliationInfo><Affiliation>Kaiser Permanente Washington Health Research Institute, 1730 Minor Ave, Seattle, WA, 98101, USA.</Affiliation></AffiliationInfo></Author><Author ValidYN="Y"><LastName>Bobb</LastName><ForeName>Jennifer F</ForeName><Initials>JF</Initials><AffiliationInfo><Affiliation>Kaiser Permanente Washington Health Research Institute, 1730 Minor Ave, Seattle, WA, 98101, USA.</Affiliation></AffiliationInfo></Author><Author ValidYN="Y"><LastName>Wong</LastName><ForeName>Edwin S</ForeName><Initials>ES</Initials><AffiliationInfo><Affiliation>Department of Health Systems and Population Health, School of Public Health, University of Washington, Box 351621, 3980 15th Ave. NE, Fourth Floor, Seattle, WA, 98195, USA.</Affiliation></AffiliationInfo><AffiliationInfo><Affiliation>Department of Veterans Affairs, Health Services Research and Development, Center of Innovation, 1660 S Columbian Way, WA, 98108, Seattle, USA.</Affiliation></AffiliationInfo></Author><Author ValidYN="Y"><LastName>Palazzo</LastName><ForeName>Lorella</ForeName><Initials>L</Initials><AffiliationInfo><Affiliation>Kaiser Permanente Washington Health Research Institute, 1730 Minor Ave, Seattle, WA, 98101, USA.</Affiliation></AffiliationInfo></Author><Author ValidYN="Y"><LastName>King</LastName><ForeName>Deborah</ForeName><Initials>D</Initials><AffiliationInfo><Affiliation>Kaiser Permanente Washington Health Research Institute, 1730 Minor Ave, Seattle, WA, 98101, USA.</Affiliation></AffiliationInfo></Author><Author ValidYN="Y"><LastName>Mogk</LastName><ForeName>Jessica</ForeName><Initials>J</Initials><AffiliationInfo><Affiliation>Kaiser Permanente Washington Health Research Institute, 1730 Minor Ave, Seattle, WA, 98101, USA.</Affiliation></AffiliationInfo></Author><Author ValidYN="Y"><LastName>Stefanik-Guizlo</LastName><ForeName>Kelsey</ForeName><Initials>K</Initials><AffiliationInfo><Affiliation>Kaiser Permanente Washington Health Research Institute, 1730 Minor Ave, Seattle, WA, 98101, USA.</Affiliation></AffiliationInfo></Author><Author ValidYN="Y"><LastName>Idu</LastName><ForeName>Abisola</ForeName><Initials>A</Initials><AffiliationInfo><Affiliation>Kaiser Permanente Washington Health Research Institute, 1730 Minor Ave, Seattle, WA, 98101, USA.</Affiliation></AffiliationInfo></Author><Author ValidYN="Y"><LastName>Key</LastName><ForeName>Dustin</ForeName><Initials>D</Initials><AffiliationInfo><Affiliation>Kaiser Permanente Washington Health Research Institute, 1730 Minor Ave, Seattle, WA, 98101, USA.</Affiliation></AffiliationInfo></Author><Author ValidYN="Y"><LastName>Fortney</LastName><ForeName>John C</ForeName><Initials>JC</Initials><AffiliationInfo><Affiliation>Department of Veterans Affairs, Health Services Research and Development, Center of Innovation, 1660 S Columbian Way, WA, 98108, Seattle, USA.</Affiliation></AffiliationInfo><AffiliationInfo><Affiliation>Department of Psychiatry and Behavioral Sciences, School of Medicine, University of Washington, Box 356560, 1959 NE Pacific Street, Seattle, WA, 98195, USA.</Affiliation></AffiliationInfo></Author><Author ValidYN="Y"><LastName>Thomas</LastName><ForeName>Rosemarie</ForeName><Initials>R</Initials><AffiliationInfo><Affiliation>Kaiser Permanente Washington Mental Health &amp; Wellness Services, 1200 SW 27th St, Renton, WA, 98057, USA.</Affiliation></AffiliationInfo></Author><Author ValidYN="Y"><LastName>McWethy</LastName><ForeName>Angela Garza</ForeName><Initials>AG</Initials><AffiliationInfo><Affiliation>Kaiser Permanente Washington Mental Health &amp; Wellness Services, 1200 SW 27th St, Renton, WA, 98057, USA.</Affiliation></AffiliationInfo></Author><Author ValidYN="Y"><LastName>Caldeiro</LastName><ForeName>Ryan M</ForeName><Initials>RM</Initials><AffiliationInfo><Affiliation>Kaiser Permanente Washington Mental Health &amp; Wellness Services, 1200 SW 27th St, Renton, WA, 98057, USA.</Affiliation></AffiliationInfo></Author><Author ValidYN="Y"><LastName>Bradley</LastName><ForeName>Katharine A</ForeName><Initials>KA</Initials><AffiliationInfo><Affiliation>Kaiser Permanente Washington Health Research Institute, 1730 Minor Ave, Seattle, WA, 98101, USA.</Affiliation></AffiliationInfo></Author></AuthorList><Language>eng</Language><DataBankList CompleteYN="Y"><DataBank><DataBankName>ClinicalTrials.gov</DataBankName><AccessionNumberList><AccessionNumber>NCT05160233</AccessionNumber></AccessionNumberList></DataBank></DataBankList><GrantList CompleteYN="Y"><Grant><GrantID>K01 AA023859</GrantID><Acronym>AA</Acronym><Agency>NIAAA NIH HHS</Agency><Country>United States</Country></Grant><Grant><GrantID>R01 DA047954</GrantID><Acronym>DA</Acronym><Agency>NIDA NIH HHS</Agency><Country>United States</Country></Grant></GrantList><PublicationTypeList><PublicationType UI="D000078325">Clinical Trial Protocol</PublicationType><PublicationType UI="D016428">Journal Article</PublicationType><PublicationType UI="D052061">Research Support, N.I.H., Extramural</PublicationType></PublicationTypeList><ArticleDate DateType="Electronic"><Year>2023</Year><Month>02</Month><Day>01</Day></ArticleDate></Article><MedlineJournalInfo><Country>England</Country><MedlineTA>Implement Sci</MedlineTA><NlmUniqueID>101258411</NlmUniqueID><ISSNLinking>1748-5908</ISSNLinking></MedlineJournalInfo><ChemicalList><Chemical><RegistryNumber>0</RegistryNumber><NameOfSubstance UI="D000701">Analgesics, Opioid</NameOfSubstance></Chemical></ChemicalList><CitationSubset>IM</CitationSubset><MeshHeadingList><MeshHeading><DescriptorName UI="D006801" MajorTopicYN="N">Humans</DescriptorName></MeshHeading><MeshHeading><DescriptorName UI="D003695" MajorTopicYN="Y">Delivery of Health Care</DescriptorName></MeshHeading><MeshHeading><DescriptorName UI="D001521" MajorTopicYN="N">Behavior Therapy</DescriptorName></MeshHeading><MeshHeading><DescriptorName UI="D000701" MajorTopicYN="N">Analgesics, Opioid</DescriptorName></MeshHeading><MeshHeading><DescriptorName UI="D009293" MajorTopicYN="Y">Opioid-Related Disorders</DescriptorName><QualifierName UI="Q000188" MajorTopicYN="N">drug therapy</QualifierName></MeshHeading><MeshHeading><DescriptorName UI="D011320" MajorTopicYN="N">Primary Health Care</DescriptorName></MeshHeading><MeshHeading><DescriptorName UI="D016032" MajorTopicYN="N">Randomized Controlled Trials as Topic</DescriptorName></MeshHeading></MeshHeadingList><KeywordList Owner="NOTNLM"><Keyword MajorTopicYN="N">Factorial trial</Keyword><Keyword MajorTopicYN="N">Implementation science</Keyword><Keyword MajorTopicYN="N">Opioid use disorders</Keyword><Keyword MajorTopicYN="N">Primary care</Keyword><Keyword MajorTopicYN="N">Substance use disorders</Keyword><Keyword MajorTopicYN="N">mHealth</Keyword></KeywordList><CoiStatement>Pear Therapeutics Inc provided digital therapeutic prescriptions at no cost to Kaiser Permanente Washington during a quality improvement pilot study that preceded this implementation trial. During the current trial, the study&#x2019;s National Institutes of Health grant (R01DA047954) pays Pear Therapeutics for digital therapeutic prescriptions and other support. JEG is a coinvestigator on a Small Business Innovation Award funded awarded to Pear Therapeutics, Inc by the National Institute on Drug Abuse, which evaluates potential improvements to reSET-O (R44DA042652). Pear Therapeutics does not provide funding to the authors.</CoiStatement></MedlineCitation><PubmedData><History><PubMedPubDate PubStatus="received"><Year>2022</Year><Month>11</Month><Day>18</Day></PubMedPubDate><PubMedPubDate PubStatus="accepted"><Year>2022</Year><Month>12</Month><Day>22</Day></PubMedPubDate><PubMedPubDate PubStatus="entrez"><Year>2023</Year><Month>2</Month><Day>2</Day><Hour>0</Hour><Minute>9</Minute></PubMedPubDate><PubMedPubDate PubStatus="pubmed"><Year>2023</Year><Month>2</Month><Day>3</Day><Hour>6</Hour><Minute>0</Minute></PubMedPubDate><PubMedPubDate PubStatus="medline"><Year>2023</Year><Month>2</Month><Day>4</Day><Hour>6</Hour><Minute>0</Minute></PubMedPubDate><PubMedPubDate PubStatus="pmc-release"><Year>2023</Year><Month>2</Month><Day>1</Day></PubMedPubDate></History><PublicationStatus>epublish</PublicationStatus><ArticleIdList><ArticleId IdType="pubmed">36726127</ArticleId><ArticleId IdType="pmc">PMC9893639</ArticleId><ArticleId IdType="doi">10.1186/s13012-022-01258-9</ArticleId><ArticleId IdType="pii">10.1186/s13012-022-01258-9</ArticleId></ArticleIdList><ReferenceList><Reference><Citation>Grant BF, Goldstein RB, Saha TD, Chou SP, Jung J, Zhang H, et al. Epidemiology of DSM-5 Alcohol Use Disorder: Results From the National Epidemiologic Survey on Alcohol and Related Conditions III. JAMA Psychiatry. 2015;72:757&#x2013;766.</Citation><ArticleIdList><ArticleId IdType="pmc">PMC5240584</ArticleId><ArticleId IdType="pubmed">26039070</ArticleId></ArticleIdList></Reference><Reference><Citation>Grant BF, Saha TD, Ruan WJ, Goldstein RB, Chou SP, Jung J, et al. Epidemiology of DSM-5 Drug Use Disorder: Results From the National Epidemiologic Survey on Alcohol and Related Conditions-III. JAMA Psychiatry. 2016;73:39&#x2013;47.</Citation><ArticleIdList><ArticleId IdType="pmc">PMC5062605</ArticleId><ArticleId IdType="pubmed">26580136</ArticleId></ArticleIdList></Reference><Reference><Citation>Mokdad AH, Marks JS, Stroup DF, Gerberding JL. Actual causes of death in the United States, 2000. JAMA. 2004;291:1238&#x2013;1245.</Citation><ArticleIdList><ArticleId IdType="pubmed">15010446</ArticleId></ArticleIdList></Reference><Reference><Citation>Degenhardt L, Hall W. Extent of illicit drug use and dependence, and their contribution to the global burden of disease. Lancet. 2012;379:55&#x2013;70.</Citation><ArticleIdList><ArticleId IdType="pubmed">22225671</ArticleId></ArticleIdList></Reference><Reference><Citation>Sacks JJ, Gonzales KR, Bouchery EE, Tomedi LE, Brewer RD. 2010 national and state costs of excessive alcohol consumption. Am J Prev Med. 2015;49:e73&#x2013;e79.</Citation><ArticleIdList><ArticleId IdType="pubmed">26477807</ArticleId></ArticleIdList></Reference><Reference><Citation>Ahmad FB, Cisewski JA, Rossen LM, Sutton P. Provisional drug overdose death counts. National Center for Health Statistics; 2022. Available from: https://www.cdc.gov/nchs/nvss/vsrr/drug-overdose-data.htm.</Citation></Reference><Reference><Citation>Barry CL, Epstein AJ, Fiellin DA, Fraenkel L, Busch SH. Estimating demand for primary care-based treatment for substance and alcohol use disorders. Addiction. 2016;111:1376&#x2013;1384.</Citation><ArticleIdList><ArticleId IdType="pmc">PMC4940268</ArticleId><ArticleId IdType="pubmed">26899802</ArticleId></ArticleIdList></Reference><Reference><Citation>U. S. Department of Health and Human Services . Facing addiction in America: The surgeon general&#x2019;s report on alcohol, drugs, and health [Internet] Washington DC: U.S. Department of Health &amp; Human Services; 2016.</Citation><ArticleIdList><ArticleId IdType="pubmed">28252892</ArticleId></ArticleIdList></Reference><Reference><Citation>Ghitza UE, Tai B. Challenges and opportunities for integrating preventive substance-use-care services in primary care through the Affordable Care Act. J Health Care Poor Underserved. 2014;25:36&#x2013;45.</Citation><ArticleIdList><ArticleId IdType="pmc">PMC3984935</ArticleId><ArticleId IdType="pubmed">24583486</ArticleId></ArticleIdList></Reference><Reference><Citation>Saitz R, Larson MJ, Labelle C, Richardson J, Samet JH. The case for chronic disease management for addiction. J Addict Med. 2008;2:55&#x2013;65.</Citation><ArticleIdList><ArticleId IdType="pmc">PMC2756688</ArticleId><ArticleId IdType="pubmed">19809579</ArticleId></ArticleIdList></Reference><Reference><Citation>Crowley RA, Kirschner N, Health, Public Policy Committee of the American College of P The integration of care for mental health, substance abuse, and other behavioral health conditions into primary care: executive summary of an American College of Physicians position paper. Ann Intern Med. 2015;163:298&#x2013;299.</Citation><ArticleIdList><ArticleId IdType="pubmed">26121401</ArticleId></ArticleIdList></Reference><Reference><Citation>Institute of Medicine . Improving the quality of health care for mental and substance-use conditions [Internet] Washington, D.C.: National Academies Press; 2006.</Citation><ArticleIdList><ArticleId IdType="pubmed">20669433</ArticleId></ArticleIdList></Reference><Reference><Citation>National Council for Behavioral Health. Implementing care for alcohol &amp; other drug use in medical settings: An extension of SBIRT. 2021. Available from: https://www.thenationalcouncil.org/wp-content/uploads/2021/04/Implementing_Care_for_Alcohol_and_Other_Drug_Use_In_Medical_Settings_-_An_Extension_of_SBIRT.pdf.</Citation></Reference><Reference><Citation>U. S. Preventive Services Task Force. Final recommendation statement: Unhealthy alcohol use in adolescents and adults: Screening and behavioral counseling interventions. 2018. Available from: https://health.gov/healthypeople/tools-action/browse-evidence-based-resources/unhealthy-alcohol-use-adolescents-and-adults-screening-and-behavioral-counseling-interventions.</Citation><ArticleIdList><ArticleId IdType="pubmed">30422199</ArticleId></ArticleIdList></Reference><Reference><Citation>U. S. Preventive Services Task Force. Krist AH, Davidson KW, Mangione CM, Barry MJ, Cabana M, et al. Screening for unhealthy drug use: US preventive services task force recommendation statement. JAMA. 2020;323:2301&#x2013;2309.</Citation><ArticleIdList><ArticleId IdType="pubmed">32515821</ArticleId></ArticleIdList></Reference><Reference><Citation>Mccrady BS. Health-care reform provides an opportunity for evidence-based alcohol treatment in the USA: The National Institute for Health and Clinical Excellence (NICE) guideline as a model: Editorial. Addiction. 2013;108:231&#x2013;232.</Citation><ArticleIdList><ArticleId IdType="pubmed">23075264</ArticleId></ArticleIdList></Reference><Reference><Citation>Jonas DE, Amick HR, Feltner C, Bobashev G, Thomas K, Wines R, et al. Pharmacotherapy for adults with alcohol use disorders in outpatient settings: a systematic review and meta-analysis. JAMA. 2014;311:1889&#x2013;1900.</Citation><ArticleIdList><ArticleId IdType="pubmed">24825644</ArticleId></ArticleIdList></Reference><Reference><Citation>Watkins KE, Ober AJ, Lamp K, Lind M, Setodji C, Osilla KC, et al. Collaborative care for opioid and alcohol use disorders in primary care: The SUMMIT randomized clinical trial. JAMA Intern Med. 2017;177:1480&#x2013;1488.</Citation><ArticleIdList><ArticleId IdType="pmc">PMC5710213</ArticleId><ArticleId IdType="pubmed">28846769</ArticleId></ArticleIdList></Reference><Reference><Citation>Babor TF, McRee BG, Kassebaum PA, Grimaldi PL, Ahmed K, Bray J. Screening, Brief Intervention, and Referral to Treatment (SBIRT): Toward a public health approach to the management of substance abuse. Subst Abus. 2007;28:7&#x2013;30.</Citation><ArticleIdList><ArticleId IdType="pubmed">18077300</ArticleId></ArticleIdList></Reference><Reference><Citation>Post EP, Metzger M, Dumas P, Lehmann L. Integrating mental health into primary care within the Veterans Health Administration. Fam Syst Health. 2010;28:83&#x2013;90.</Citation><ArticleIdList><ArticleId IdType="pubmed">20695668</ArticleId></ArticleIdList></Reference><Reference><Citation>Campbell CI, Saxon AJ, Boudreau DM, Wartko PD, Bobb JF, Lee AK, et al. PRimary Care Opioid Use Disorders treatment (PROUD) trial protocol: A pragmatic, cluster-randomized implementation trial in primary care for opioid use disorder treatment. Addict Sci Clin Pract. 2021;16:9.</Citation><ArticleIdList><ArticleId IdType="pmc">PMC7849121</ArticleId><ArticleId IdType="pubmed">33517894</ArticleId></ArticleIdList></Reference><Reference><Citation>Sayre M, Lapham GT, Lee AK, Oliver M, Bobb JF, Caldeiro RM, et al. Routine assessment of symptoms of substance use disorders in primary care: Prevalence and severity of reported symptoms. J Gen Intern Med. 2020;35:1111&#x2013;1119.</Citation><ArticleIdList><ArticleId IdType="pmc">PMC7174482</ArticleId><ArticleId IdType="pubmed">31974903</ArticleId></ArticleIdList></Reference><Reference><Citation>Lapham GT, Lee AK, Caldeiro RM, Glass JE, Carrell DS, Richards JE, et al. Prevalence of behavioral health conditions across frequency of cannabis use among adult primary care patients in Washington state. J Gen Intern Med. 2018;33:1833&#x2013;1835.</Citation><ArticleIdList><ArticleId IdType="pmc">PMC6206344</ArticleId><ArticleId IdType="pubmed">29992423</ArticleId></ArticleIdList></Reference><Reference><Citation>Glass JE, Mowbray OP, Link BG, Kristjansson SD, Bucholz KK. Alcohol stigma and persistence of alcohol and other psychiatric disorders: A modified labeling theory approach. Drug Alcohol Depend. 2013;133:685&#x2013;692.</Citation><ArticleIdList><ArticleId IdType="pmc">PMC3980578</ArticleId><ArticleId IdType="pubmed">24071569</ArticleId></ArticleIdList></Reference><Reference><Citation>Chernof BA, Sherman SE, Lanto AB, Lee ML, Yano EM, Rubenstein LV. Health habit counseling amidst competing demands: effects of patient health habits and visit characteristics. Med Care. 1999;37:738&#x2013;747.</Citation><ArticleIdList><ArticleId IdType="pubmed">10448717</ArticleId></ArticleIdList></Reference><Reference><Citation>Jaen CR, Stange KC, Nutting PA. Competing demands of primary care: a model for the delivery of clinical preventive services. J Fam Pract. 1994;38:166&#x2013;171.</Citation><ArticleIdList><ArticleId IdType="pubmed">8308509</ArticleId></ArticleIdList></Reference><Reference><Citation>Prendergast M, Podus D, Finney J, Greenwell L, Roll J. Contingency management for treatment of substance use disorders: a meta-analysis. Addiction. 2006;101:1546&#x2013;1560.</Citation><ArticleIdList><ArticleId IdType="pubmed">17034434</ArticleId></ArticleIdList></Reference><Reference><Citation>Gates PJ, Sabioni P, Copeland J, Le Foll B, Gowing L. Psychosocial interventions for cannabis use disorder. Cochrane Database Syst Rev. 2016;2016:CD005336.</Citation><ArticleIdList><ArticleId IdType="pmc">PMC4914383</ArticleId><ArticleId IdType="pubmed">27149547</ArticleId></ArticleIdList></Reference><Reference><Citation>Dutra L, Stathopoulou G, Basden SL, Leyro TM, Powers MB, Otto MW. A meta-analytic review of psychosocial interventions for substance use disorders. Am J Psychiatry. 2008;165:179&#x2013;187.</Citation><ArticleIdList><ArticleId IdType="pubmed">18198270</ArticleId></ArticleIdList></Reference><Reference><Citation>Lussier JP, Heil SH, Mongeon JA, Badger GJ, Higgins ST. A meta-analysis of voucher-based reinforcement therapy for substance use disorders. Addiction. 2006;101:192&#x2013;203.</Citation><ArticleIdList><ArticleId IdType="pubmed">16445548</ArticleId></ArticleIdList></Reference><Reference><Citation>Magill M, Ray LA. Cognitive-behavioral treatment with adult alcohol and illicit drug users: a meta-analysis of randomized controlled trials. Journal of studies on alcohol and drugs. 2009;70:516&#x2013;527.</Citation><ArticleIdList><ArticleId IdType="pmc">PMC2696292</ArticleId><ArticleId IdType="pubmed">19515291</ArticleId></ArticleIdList></Reference><Reference><Citation>Carroll KM. Dissemination of evidence-based practices: how far we&#x2019;ve come, and how much further we&#x2019;ve got to go. Addiction. 2012;107:1031&#x2013;1033.</Citation><ArticleIdList><ArticleId IdType="pubmed">22324509</ArticleId></ArticleIdList></Reference><Reference><Citation>Kiluk BD, Carroll KM. New developments in behavioral treatments for substance use disorders. Curr Psychiatry Rep. 2013;15:420.</Citation><ArticleIdList><ArticleId IdType="pmc">PMC3878068</ArticleId><ArticleId IdType="pubmed">24173656</ArticleId></ArticleIdList></Reference><Reference><Citation>Lapham G, Boudreau DM, Johnson EA, Bobb JF, Matthews AG, McCormack J, et al. Prevalence and treatment of opioid use disorders among primary care patients in six health systems. Drug Alcohol Depend. 2020;207:107732.</Citation><ArticleIdList><ArticleId IdType="pmc">PMC7158756</ArticleId><ArticleId IdType="pubmed">31835068</ArticleId></ArticleIdList></Reference><Reference><Citation>Boudreau DM, Lapham G, Johnson EA, Bobb JF, Matthews AG, McCormack J, et al. Documented opioid use disorder and its treatment in primary care patients across six U.S. health systems. J Subst Abuse Treat. 2020;112S:41&#x2013;48.</Citation><ArticleIdList><ArticleId IdType="pmc">PMC7107675</ArticleId><ArticleId IdType="pubmed">32220410</ArticleId></ArticleIdList></Reference><Reference><Citation>Hickman M, Steer C, Tilling K, Lim AG, Marsden J, Millar T, et al. The impact of buprenorphine and methadone on mortality: a primary care cohort study in the United Kingdom: burpenorphine vs methadone on mortality risk. Addiction. 2018;113:1461&#x2013;1476.</Citation><ArticleIdList><ArticleId IdType="pmc">PMC6282737</ArticleId><ArticleId IdType="pubmed">29672985</ArticleId></ArticleIdList></Reference><Reference><Citation>Carroll KM, Ball SA, Martino S, Nich C, Babuscio TA, Nuro KF, et al. Computer-assisted delivery of cognitive-behavioral therapy for addiction: a randomized trial of CBT4CBT. Am J Psychiatry. 2008;165:881&#x2013;888.</Citation><ArticleIdList><ArticleId IdType="pmc">PMC2562873</ArticleId><ArticleId IdType="pubmed">18450927</ArticleId></ArticleIdList></Reference><Reference><Citation>Gustafson DH, McTavish FM, Chih MY, Atwood AK, Johnson RA, Boyle MG, et al. A smartphone application to support recovery from alcoholism: a randomized clinical trial. JAMA Psychiatry. 2014;71:566&#x2013;572.</Citation><ArticleIdList><ArticleId IdType="pmc">PMC4016167</ArticleId><ArticleId IdType="pubmed">24671165</ArticleId></ArticleIdList></Reference><Reference><Citation>Campbell AN, Nunes EV, Matthews AG, Stitzer M, Miele GM, Polsky D, et al. Internet-delivered treatment for substance abuse: a multisite randomized controlled trial. Am J Psychiatry. 2014;171:683&#x2013;690.</Citation><ArticleIdList><ArticleId IdType="pmc">PMC4079279</ArticleId><ArticleId IdType="pubmed">24700332</ArticleId></ArticleIdList></Reference><Reference><Citation>Hermes ED, Lyon AR, Schueller SM, Glass JE. Measuring the Implementation of Behavioral Intervention Technologies: Recharacterization of Established Outcomes. J Med Internet Res. 2019;21:e11752.</Citation><ArticleIdList><ArticleId IdType="pmc">PMC6367669</ArticleId><ArticleId IdType="pubmed">30681966</ArticleId></ArticleIdList></Reference><Reference><Citation>Storholm ED, Ober AJ, Hunter SB, Becker KM, Iyiewuare PO, Pham C, et al. Barriers to integrating the continuum of care for opioid and alcohol use disorders in primary care: A qualitative longitudinal study. Journal of Substance Abuse Treatment. 2017;83:45&#x2013;54.</Citation><ArticleIdList><ArticleId IdType="pmc">PMC5728181</ArticleId><ArticleId IdType="pubmed">29129195</ArticleId></ArticleIdList></Reference><Reference><Citation>McNeely J, Kumar PC, Rieckmann T, Sedlander E, Farkas S, Chollak C, et al. Barriers and facilitators affecting the implementation of substance use screening in primary care clinics: a qualitative study of patients, providers, and staff. Addict Sci Clin Pract. 2018;13:8.</Citation><ArticleIdList><ArticleId IdType="pmc">PMC5890352</ArticleId><ArticleId IdType="pubmed">29628018</ArticleId></ArticleIdList></Reference><Reference><Citation>Marsch LA, Guarino H, Acosta M, Aponte-Melendez Y, Cleland C, Grabinski M, et al. Web-based behavioral treatment for substance use disorders as a partial replacement of standard methadone maintenance treatment. J Subst Abuse Treat. 2014;46:43&#x2013;51.</Citation><ArticleIdList><ArticleId IdType="pmc">PMC3839618</ArticleId><ArticleId IdType="pubmed">24060350</ArticleId></ArticleIdList></Reference><Reference><Citation>Campbell AN, Turrigiano E, Moore M, Miele GM, Rieckmann T, Hu MC, et al. Acceptability of a web-based community reinforcement approach for substance use disorders with treatment-seeking American Indians/Alaska Natives. Community Ment Health J. 2015;51:393&#x2013;403.</Citation><ArticleIdList><ArticleId IdType="pmc">PMC4295007</ArticleId><ArticleId IdType="pubmed">25022913</ArticleId></ArticleIdList></Reference><Reference><Citation>Campbell ANC, Montgomery L, Sanchez K, Pavlicova M, Hu M, Newville H, et al. Racial/ethnic subgroup differences in outcomes and acceptability of an Internet-delivered intervention for substance use disorders. J Ethn Subst Abuse. 2017;16:1&#x2013;19.</Citation><ArticleIdList><ArticleId IdType="pmc">PMC5624812</ArticleId><ArticleId IdType="pubmed">28368740</ArticleId></ArticleIdList></Reference><Reference><Citation>Maricich YA, Xiong X, Gerwien R, Kuo A, Velez F, Imbert B, et al. Real-world evidence for a prescription digital therapeutic to treat opioid use disorder. Current Medical Research and Opinion. 2021;37:175&#x2013;183.</Citation><ArticleIdList><ArticleId IdType="pubmed">33140981</ArticleId></ArticleIdList></Reference><Reference><Citation>Xiong X, Braun S, Stitzer M, Luderer H, Shafai G, Hare B, et al. Evaluation of real-world outcomes associated with use of a prescription digital therapeutic to treat substance use disorders. American J Addict. 2022;32:ajad.13346.</Citation><ArticleIdList><ArticleId IdType="pmc">PMC10091717</ArticleId><ArticleId IdType="pubmed">36264211</ArticleId></ArticleIdList></Reference><Reference><Citation>Shah N, Velez FF, Colman S, Kauffman L, Ruetsch C, Anastassopoulos K, et al. Real-World Reductions in Healthcare Resource Utilization over 6 Months in Patients with Substance Use Disorders Treated with a Prescription Digital Therapeutic. Adv Ther. 2022;39:4146&#x2013;4156.</Citation><ArticleIdList><ArticleId IdType="pmc">PMC9273919</ArticleId><ArticleId IdType="pubmed">35819569</ArticleId></ArticleIdList></Reference><Reference><Citation>Velez FF, Anastassopoulos KP, Colman S, Shah N, Kauffman L, Murphy SM, et al. Reduced Healthcare Resource Utilization in Patients with Opioid Use Disorder in the 12 Months After Initiation of a Prescription Digital Therapeutic. Adv Ther. 2022;39:4131&#x2013;4145.</Citation><ArticleIdList><ArticleId IdType="pmc">PMC9402736</ArticleId><ArticleId IdType="pubmed">35799080</ArticleId></ArticleIdList></Reference><Reference><Citation>Graham AK, Greene CJ, Powell T, Lieponis P, Lunsford A, Peralta CD, et al. Lessons learned from service design of a trial of a digital mental health service: Informing implementation in primary care clinics. Translational Behavioral Medicine. 2020;10:598&#x2013;605.</Citation><ArticleIdList><ArticleId IdType="pmc">PMC7413191</ArticleId><ArticleId IdType="pubmed">32766862</ArticleId></ArticleIdList></Reference><Reference><Citation>Glass JE, Matson TE, Lim C, Hartzler AL, Kimbel K, Lee AK, et al. Approaches for Implementing App-Based Digital Treatments for Drug Use Disorders Into Primary Care: A Qualitative, User-Centered Design Study of Patient Perspectives. J Med Internet Res. 2021;23:e25866.</Citation><ArticleIdList><ArticleId IdType="pmc">PMC8293157</ArticleId><ArticleId IdType="pubmed">34255666</ArticleId></ArticleIdList></Reference><Reference><Citation>Mares ML, Gustafson DH, Glass JE, Quanbeck A, McDowell H, McTavish F, et al. Implementing an mHealth system for substance use disorders in primary care: a mixed methods study of clinicians&#x2019; initial expectations and first year experiences. BMC Med Inform Decis Mak. 2016;16:126.</Citation><ArticleIdList><ArticleId IdType="pmc">PMC5043521</ArticleId><ArticleId IdType="pubmed">27687632</ArticleId></ArticleIdList></Reference><Reference><Citation>Knowles SE, Lovell K, Bower P, Gilbody S, Littlewood E, Lester H. Patient experience of computerised therapy for depression in primary care. BMJ open. 2015;5:e008581.</Citation><ArticleIdList><ArticleId IdType="pmc">PMC4679833</ArticleId><ArticleId IdType="pubmed">26621513</ArticleId></ArticleIdList></Reference><Reference><Citation>Gilbody S, Littlewood E, Hewitt C, Brierley G, Tharmanathan P, Araya R, et al. Computerised cognitive behaviour therapy (cCBT) as treatment for depression in primary care (REEACT trial): large scale pragmatic randomised controlled trial. BMJ. 2015;351:h5627.</Citation><ArticleIdList><ArticleId IdType="pmc">PMC4641883</ArticleId><ArticleId IdType="pubmed">26559241</ArticleId></ArticleIdList></Reference><Reference><Citation>Mohr D, Cuijpers P, Lehman K. Supportive Accountability: A Model for Providing Human Support to Enhance Adherence to eHealth Interventions. Journal of Medical Internet Research. 2011;13:e30.</Citation><ArticleIdList><ArticleId IdType="pmc">PMC3221353</ArticleId><ArticleId IdType="pubmed">21393123</ArticleId></ArticleIdList></Reference><Reference><Citation>Thies K, Anderson D, Cramer B. Lack of Adoption of a Mobile App to Support Patient Self-Management of Diabetes and Hypertension in a Federally Qualified Health Center: Interview Analysis of Staff and Patients in a Failed Randomized Trial. JMIR Hum Factors. 2017;4:e24.</Citation><ArticleIdList><ArticleId IdType="pmc">PMC5645643</ArticleId><ArticleId IdType="pubmed">28974481</ArticleId></ArticleIdList></Reference><Reference><Citation>Quanbeck A, Gustafson DH, Marsch LA, Chih MY, Kornfield R, McTavish F, et al. Implementing a Mobile Health System to Integrate the Treatment of Addiction Into Primary Care: A Hybrid Implementation-Effectiveness Study. J Med Internet Res. 2018;20:e37.</Citation><ArticleIdList><ArticleId IdType="pmc">PMC5811649</ArticleId><ArticleId IdType="pubmed">29382624</ArticleId></ArticleIdList></Reference><Reference><Citation>Quanbeck AR, Gustafson DH, Marsch LA, McTavish F, Brown RT, Mares M-L, et al. Integrating addiction treatment into primary care using mobile health technology: protocol for an implementation research study. Implementation Science. 2014;9:65.</Citation><ArticleIdList><ArticleId IdType="pmc">PMC4072605</ArticleId><ArticleId IdType="pubmed">24884976</ArticleId></ArticleIdList></Reference><Reference><Citation>Gilbody S, Brabyn S, Lovell K, Kessler D, Devlin T, Smith L, et al. Telephone-supported computerised cognitive-behavioural therapy: REEACT-2 large-scale pragmatic randomised controlled trial. Br J Psychiatry. 2017;210:362&#x2013;367.</Citation><ArticleIdList><ArticleId IdType="pubmed">28254959</ArticleId></ArticleIdList></Reference><Reference><Citation>Johansson R, Andersson G. Internet-based psychological treatments for depression. Expert Rev Neurother. 2012;12:861&#x2013;869.</Citation><ArticleIdList><ArticleId IdType="pubmed">22853793</ArticleId></ArticleIdList></Reference><Reference><Citation>Andersson G, Cuijpers P. Internet-based and other computerized psychological treatments for adult depression: a meta-analysis. Cogn Behav Ther. 2009;38:196&#x2013;205.</Citation><ArticleIdList><ArticleId IdType="pubmed">20183695</ArticleId></ArticleIdList></Reference><Reference><Citation>Park LS, Chih M-Y, Stephenson C, Schumacher N, Brown R, Gustafson D, et al. Testing an mHealth System for Individuals With Mild to Moderate Alcohol Use Disorders: Protocol for a Type 1 Hybrid Effectiveness-Implementation Trial. JMIR Res Protoc. 2022;11:e31109.</Citation><ArticleIdList><ArticleId IdType="pmc">PMC8900897</ArticleId><ArticleId IdType="pubmed">35179502</ArticleId></ArticleIdList></Reference><Reference><Citation>Dedert EA, McDuffie JR, Stein R, McNiel JM, Kosinski AS, Freiermuth CE, et al. Electronic Interventions for Alcohol Misuse and Alcohol Use Disorders: A Systematic Review. Annals of Internal Medicine. 2015;163:205.</Citation><ArticleIdList><ArticleId IdType="pmc">PMC4837467</ArticleId><ArticleId IdType="pubmed">26237752</ArticleId></ArticleIdList></Reference><Reference><Citation>Lau AY, Piper K, Bokor D, Martin P, Lau VS, Coiera E. Challenges During Implementation of a Patient-Facing Mobile App for Surgical Rehabilitation: Feasibility Study. JMIR Hum Factors. 2017;4:e31.</Citation><ArticleIdList><ArticleId IdType="pmc">PMC5740262</ArticleId><ArticleId IdType="pubmed">29217504</ArticleId></ArticleIdList></Reference><Reference><Citation>Bickel WK, Marsch LA, Buchhalter AR, Badger GJ. Computerized behavior therapy for opioid-dependent outpatients: a randomized controlled trial. Exp Clin Psychopharmacol. 2008;16:132&#x2013;143.</Citation><ArticleIdList><ArticleId IdType="pmc">PMC2746734</ArticleId><ArticleId IdType="pubmed">18489017</ArticleId></ArticleIdList></Reference><Reference><Citation>Christensen DR, Landes RD, Jackson L, Marsch LA, Mancino MJ, Chopra MP, et al. Adding an Internet-delivered treatment to an efficacious treatment package for opioid dependence. J Consult Clin Psychol. 2014;82:964&#x2013;972.</Citation><ArticleIdList><ArticleId IdType="pmc">PMC4244262</ArticleId><ArticleId IdType="pubmed">25090043</ArticleId></ArticleIdList></Reference><Reference><Citation>Maricich YA, Nunes EV, Campbell ANC, Botbyl JD, Luderer HF. Safety and efficacy of a digital therapeutic for substance use disorder: Secondary analysis of data from a NIDA clinical trials network study. Substance Abuse. 2022;43:937&#x2013;942.</Citation><ArticleIdList><ArticleId IdType="pubmed">35420979</ArticleId></ArticleIdList></Reference><Reference><Citation>Ritchie MJ, Dollar KM, Miller CJ, Oliver KA, Smith JL, Lindsay JA, et al. Using implementation facilitation to improve care in the Veterans Health Administration (Version 2) Quality Enhancement Research Initiative (QUERI) for Team-Based Behavioral Health: Veterans Health Administration; 2017.</Citation></Reference><Reference><Citation>Harvey G, Kitson A. PARIHS revisited: from heuristic to integrated framework for the successful implementation of knowledge into practice. Implement Sci. 2016;11:33.</Citation><ArticleIdList><ArticleId IdType="pmc">PMC4807546</ArticleId><ArticleId IdType="pubmed">27013464</ArticleId></ArticleIdList></Reference><Reference><Citation>Stetler CB, Legro MW, Rycroft-Malone J, Bowman C, Curran G, Guihan M, et al. Role of &#x201c;external facilitation&#x201d; in implementation of research findings: a qualitative evaluation of facilitation experiences in the Veterans Health Administration. Implement Sci. 2006;1:23.</Citation><ArticleIdList><ArticleId IdType="pmc">PMC1635058</ArticleId><ArticleId IdType="pubmed">17049080</ArticleId></ArticleIdList></Reference><Reference><Citation>Glass JE, Bobb JF, Lee AK, Richards JE, Lapham GT, Ludman E, et al. Study protocol: A cluster-randomized trial implementing Sustained Patient-centered Alcohol-related Care (SPARC trial) Implement Sci. 2018;13:108.</Citation><ArticleIdList><ArticleId IdType="pmc">PMC6080376</ArticleId><ArticleId IdType="pubmed">30081930</ArticleId></ArticleIdList></Reference><Reference><Citation>Kottke TE, Solberg LI, Brekke ML, Conn SA, Maxwell P, Brekke MJ. A controlled trial to integrate smoking cessation advice into primary care practice: Doctors Helping Smokers. Round III. J Fam Pract. 1992;34:701&#x2013;708.</Citation><ArticleIdList><ArticleId IdType="pubmed">1593243</ArticleId></ArticleIdList></Reference><Reference><Citation>Fortney J, Enderle M, McDougall S, Clothier J, Otero J, Altman L, et al. Implementation outcomes of evidence-based quality improvement for depression in VA community based outpatient clinics. Implement Sci. 2012;7:30.</Citation><ArticleIdList><ArticleId IdType="pmc">PMC3353178</ArticleId><ArticleId IdType="pubmed">22494428</ArticleId></ArticleIdList></Reference><Reference><Citation>Cockburn J, Ruth D, Silagy C, Dobbin M, Reid Y, Scollo M, et al. Randomised trial of three approaches for marketing smoking cessation programmes to Australian general practitioners. BMJ. 1992;304:691&#x2013;694.</Citation><ArticleIdList><ArticleId IdType="pmc">PMC1881508</ArticleId><ArticleId IdType="pubmed">1571645</ArticleId></ArticleIdList></Reference><Reference><Citation>Gustafson DH, Quanbeck AR, Robinson JM, Ford JH, Pulvermacher A, French MT, et al. Which elements of improvement collaboratives are most effective? A cluster-randomized trial: NIATx 200 main outcomes. Addiction. 2013;108:1145&#x2013;1157.</Citation><ArticleIdList><ArticleId IdType="pmc">PMC3651751</ArticleId><ArticleId IdType="pubmed">23316787</ArticleId></ArticleIdList></Reference><Reference><Citation>Baskerville NB, Liddy C, Hogg W. Systematic review and meta-analysis of practice facilitation within primary care settings. The Annals of Family Medicine. 2012;10:63&#x2013;74.</Citation><ArticleIdList><ArticleId IdType="pmc">PMC3262473</ArticleId><ArticleId IdType="pubmed">22230833</ArticleId></ArticleIdList></Reference><Reference><Citation>Gagliardi AR, Legare F, Brouwers MC, Webster F, Badley E, Straus S. Patient-mediated knowledge translation (PKT) interventions for clinical encounters: a systematic review. Implement Sci. 2016;11:26.</Citation><ArticleIdList><ArticleId IdType="pmc">PMC4770686</ArticleId><ArticleId IdType="pubmed">26923462</ArticleId></ArticleIdList></Reference><Reference><Citation>Curran GM, Bauer M, Mittman B, Pyne JM, Stetler C. Effectiveness-implementation hybrid designs: combining elements of clinical effectiveness and implementation research to enhance public health impact. Med Care. 2012;50:217&#x2013;226.</Citation><ArticleIdList><ArticleId IdType="pmc">PMC3731143</ArticleId><ArticleId IdType="pubmed">22310560</ArticleId></ArticleIdList></Reference><Reference><Citation>Carroll C, Patterson M, Wood S, Booth A, Rick J, Balain S. A conceptual framework for implementation fidelity. Implementation Sci. 2007;2:40.</Citation><ArticleIdList><ArticleId IdType="pmc">PMC2213686</ArticleId><ArticleId IdType="pubmed">18053122</ArticleId></ArticleIdList></Reference><Reference><Citation>Proctor E, Silmere H, Raghavan R, Hovmand P, Aarons G, Bunger A, et al. Outcomes for implementation research: conceptual distinctions, measurement challenges, and research agenda. Adm Policy Ment Health. 2011;38:65&#x2013;76.</Citation><ArticleIdList><ArticleId IdType="pmc">PMC3068522</ArticleId><ArticleId IdType="pubmed">20957426</ArticleId></ArticleIdList></Reference><Reference><Citation>Fortney JC, Pyne JM, Burgess JF. Population-level cost-effectiveness of implementing evidence-based practices into routine care. Health Serv Res. 2014;49:1832&#x2013;1851.</Citation><ArticleIdList><ArticleId IdType="pmc">PMC4254127</ArticleId><ArticleId IdType="pubmed">25328029</ArticleId></ArticleIdList></Reference><Reference><Citation>Chan A-W, Tetzlaff JM, Altman DG, Laupacis A, G&#xf8;tzsche PC, Krle&#x17e;a-Jeri&#x107; K, et al. SPIRIT 2013 Statement: Defining Standard Protocol Items for Clinical Trials. Ann Intern Med. 2013;158:200.</Citation><ArticleIdList><ArticleId IdType="pmc">PMC5114123</ArticleId><ArticleId IdType="pubmed">23295957</ArticleId></ArticleIdList></Reference><Reference><Citation>Maricich YA, Gerwien R, Kuo A, Malone DC, Velez FF. Real-world use and clinical outcomes after 24 weeks of treatment with a prescription digital therapeutic for opioid use disorder. Hospital Practice. 2021;49:348&#x2013;355.</Citation><ArticleIdList><ArticleId IdType="pubmed">34461801</ArticleId></ArticleIdList></Reference><Reference><Citation>Chambers DA, Glasgow RE, Stange KC. The dynamic sustainability framework: addressing the paradox of sustainment amid ongoing change. Implement Sci. 2013;8:117.</Citation><ArticleIdList><ArticleId IdType="pmc">PMC3852739</ArticleId><ArticleId IdType="pubmed">24088228</ArticleId></ArticleIdList></Reference><Reference><Citation>Nilsen P. Making sense of implementation theories, models and frameworks. Implementation Science. 2015;10:53.</Citation><ArticleIdList><ArticleId IdType="pmc">PMC4406164</ArticleId><ArticleId IdType="pubmed">25895742</ArticleId></ArticleIdList></Reference><Reference><Citation>Helfrich CD, Li Y-F, Sharp ND, Sales AE. Organizational readiness to change assessment (ORCA): development of an instrument based on the Promoting Action on Research in Health Services (PARIHS) framework. Implementation Science. 2009;4:38.</Citation><ArticleIdList><ArticleId IdType="pmc">PMC2716295</ArticleId><ArticleId IdType="pubmed">19594942</ArticleId></ArticleIdList></Reference><Reference><Citation>Glass JE, Tiffany B, Matson TE, Lim C, Gundersen G, Kimbel K, et al. Approaches for implementing digital interventions for alcohol use disorders in primary care: A qualitative, user-centered design study. Implementation Research and Practice. 2022;3:263348952211352.</Citation><ArticleIdList><ArticleId IdType="pmc">PMC9924279</ArticleId><ArticleId IdType="pubmed">37091101</ArticleId></ArticleIdList></Reference><Reference><Citation>Ritchie MJ, Dollar KM, Miller CJ, Smith, JL, Oliver KA, Kim B, et al. Using implementation facilitation to improve healthcare (Version 3). Veterans Health Administration, Behavioral Health Quality Enhancement Research Initiative (QUERI); 2020. Available from: https://www.queri.research.va.gov/tools/Facilitation-Manual.pdf.</Citation></Reference><Reference><Citation>Real Balance Global Wellness Services Inc. 2022. Available from: https://realbalance.com/.</Citation></Reference><Reference><Citation>Proctor EK, Powell BJ, McMillen JC. Implementation strategies: recommendations for specifying and reporting. Implement Sci. 2013;8:139.</Citation><ArticleIdList><ArticleId IdType="pmc">PMC3882890</ArticleId><ArticleId IdType="pubmed">24289295</ArticleId></ArticleIdList></Reference><Reference><Citation>Richards JE, Bobb JF, Lee AK, Lapham GT, Williams EC, Glass JE, et al. Integration of screening, assessment, and treatment for cannabis and other drug use disorders in primary care: An evaluation in three pilot sites. Drug Alcohol Depend. 2019;201:134&#x2013;141.</Citation><ArticleIdList><ArticleId IdType="pmc">PMC6642904</ArticleId><ArticleId IdType="pubmed">31212213</ArticleId></ArticleIdList></Reference><Reference><Citation>Matson TE, Lapham GT, Bobb JF, Johnson E, Richards JE, Lee AK, et al. Cannabis use, other drug use, and risk of subsequent acute care in primary care patients. Drug Alcohol Depend. 2020;108227:108227.</Citation><ArticleIdList><ArticleId IdType="pmc">PMC7896808</ArticleId><ArticleId IdType="pubmed">32911133</ArticleId></ArticleIdList></Reference><Reference><Citation>Glasgow RE, Phillips SM, Sanchez MA. Implementation science approaches for integrating eHealth research into practice and policy. Int J Med Inform. 2014;83:e1&#x2013;11.</Citation><ArticleIdList><ArticleId IdType="pubmed">23910896</ArticleId></ArticleIdList></Reference><Reference><Citation>Glasgow RE, Vogt TM, Boles SM. Evaluating the public health impact of health promotion interventions: the RE-AIM framework. Am J Public Health. 1999;89:1322&#x2013;1327.</Citation><ArticleIdList><ArticleId IdType="pmc">PMC1508772</ArticleId><ArticleId IdType="pubmed">10474547</ArticleId></ArticleIdList></Reference><Reference><Citation>Pear Therapeutics. reSET-O Digital Mobile Therapy: Clinician Directions for Use. Boston; 2018. Report No.: #CDFU-0002, Rev A</Citation></Reference><Reference><Citation>Pear Therapeutics. reSET Digital Mobile Therapy: Clinician Directions for Use. Boston; 2018. Report No.: #CDFU-0001, Rev D</Citation></Reference><Reference><Citation>Kugler KC, Trail JB, Dziak JJ, Collins LM. Effect coding versus dummy coding in analysis of data from factorial experiments. University Park, PA: The Methodology Center, Pennsylvania State University; 2012.</Citation></Reference><Reference><Citation>Wu CJ, Hamada MS. Experiments: planning, analysis, and optimization, vol. 552. Wiley; 2011.</Citation></Reference><Reference><Citation>Collins LM, Dziak JJ, Kugler KC, Trail JB. Factorial experiments: efficient tools for evaluation of intervention components. Am J Prev Med. 2014;47:498&#x2013;504.</Citation><ArticleIdList><ArticleId IdType="pmc">PMC4171184</ArticleId><ArticleId IdType="pubmed">25092122</ArticleId></ArticleIdList></Reference><Reference><Citation>Eldridge S, Campbell M, Campbell M, Drahota-Towns A, Giraudeau B, Higgins J et al. Revised Cochrane risk of bias tool for randomized trials (RoB 2.0): additional considerations for cluster-randomized trials. 2016.</Citation></Reference><Reference><Citation>Eldridge S, Kerry S, Torgerson DJ. Bias in identifying and recruiting participants in cluster randomised trials: what can be done? BMJ. 2009;339:b4006.</Citation><ArticleIdList><ArticleId IdType="pubmed">19819928</ArticleId></ArticleIdList></Reference><Reference><Citation>Bobb JF, Qiu H, Matthews AG, McCormack J, Bradley KA. Addressing identification bias in the design and analysis of cluster-randomized pragmatic trials: a case study. Trials. 2020;21:1&#x2013;12.</Citation><ArticleIdList><ArticleId IdType="pmc">PMC7092580</ArticleId><ArticleId IdType="pubmed">32293514</ArticleId></ArticleIdList></Reference><Reference><Citation>Bobb J, Cook A, Shortreed S, Glass J, Vollmer W. Rethinking Clinical Trials: A Living Textbook of Pragmatic Clinical Trials [Internet] Bethesda, MD: NIH Health Care Systems Research Collaboratory; 2019. Experimental designs and randomization schemes: designing to avoid identification bias.</Citation></Reference><Reference><Citation>Dakin H, Gray A. Economic evaluation of factorial randomised controlled trials: challenges, methods and recommendations: Factorial trials: Methods for economic evaluation. Statist Med. 2017;36:2814&#x2013;2830.</Citation><ArticleIdList><ArticleId IdType="pmc">PMC5599939</ArticleId><ArticleId IdType="pubmed">28470760</ArticleId></ArticleIdList></Reference><Reference><Citation>Baker JJ. Activity-based Costing and Activity-based Management for Health Care. Jones &amp; Bartlett Learning; 1998.</Citation></Reference><Reference><Citation>Yeung K, Richards J, Goemer E, Lozano P, Lapham G, Williams E, et al. Costs of using evidence-based implementation strategies for behavioral health integration in a large primary care system. Health Serv Res. 2020;55:913&#x2013;923.</Citation><ArticleIdList><ArticleId IdType="pmc">PMC7704468</ArticleId><ArticleId IdType="pubmed">33258127</ArticleId></ArticleIdList></Reference><Reference><Citation>Miller CJ, Barnett ML, Baumann AA, Gutner CA, Wiltsey-Stirman S. The FRAME-IS: a framework for documenting modifications to implementation strategies in healthcare. Implement Sci. 2021;16:36.</Citation><ArticleIdList><ArticleId IdType="pmc">PMC8024675</ArticleId><ArticleId IdType="pubmed">33827716</ArticleId></ArticleIdList></Reference><Reference><Citation>Wiltsey Stirman S, Baumann AA, Miller CJ. The FRAME: an expanded framework for reporting adaptations and modifications to evidence-based interventions. Implementation Sci. 2019;14:58.</Citation><ArticleIdList><ArticleId IdType="pmc">PMC6554895</ArticleId><ArticleId IdType="pubmed">31171014</ArticleId></ArticleIdList></Reference><Reference><Citation>Hamilton AB. Qualitative methods in rapid turn around health services research. Department of Veterans Affairs; 2013. Available from: https://www.hsrd.research.va.gov/for_researchers/cyber_seminars/archives/780-notes.pdf.</Citation></Reference><Reference><Citation>Hamilton AB, Finley EP. Qualitative methods in implementation research: An introduction. Psychiatry Research. 2019;280:112516.</Citation><ArticleIdList><ArticleId IdType="pmc">PMC7023962</ArticleId><ArticleId IdType="pubmed">31437661</ArticleId></ArticleIdList></Reference><Reference><Citation>Bach-Mortensen AM, Lange BCL, Montgomery P. Barriers and facilitators to implementing evidence-based interventions among third sector organisations: a systematic review. Implementation Sci. 2018;13:103.</Citation><ArticleIdList><ArticleId IdType="pmc">PMC6065156</ArticleId><ArticleId IdType="pubmed">30060744</ArticleId></ArticleIdList></Reference></ReferenceList></PubmedData></PubmedArticle></PubmedArticleSet>