<?xml version="1.0" ?>
<!DOCTYPE PubmedArticleSet PUBLIC "-//NLM//DTD PubMedArticle, 1st January 2025//EN" "https://dtd.nlm.nih.gov/ncbi/pubmed/out/pubmed_250101.dtd">
<PubmedArticleSet>
<PubmedArticle><MedlineCitation Status="PubMed-not-MEDLINE" Owner="NLM"><PMID Version="1">36619214</PMID><DateRevised><Year>2023</Year><Month>02</Month><Day>21</Day></DateRevised><Article PubModel="Print-Electronic"><Journal><ISSN IssnType="Print">2214-2509</ISSN><JournalIssue CitedMedium="Print"><Volume>31</Volume><PubDate><Year>2023</Year></PubDate></JournalIssue><Title>IDCases</Title><ISOAbbreviation>IDCases</ISOAbbreviation></Journal><ArticleTitle>Diagnosis of type 2 diabetes in a patient with acute sinusitis and COVID-19 in Colombia.</ArticleTitle><Pagination><StartPage>e01664</StartPage><MedlinePgn>e01664</MedlinePgn></Pagination><ELocationID EIdType="pii" ValidYN="Y">e01664</ELocationID><ELocationID EIdType="doi" ValidYN="Y">10.1016/j.idcr.2022.e01664</ELocationID><Abstract><AbstractText>During the COVID-19 pandemic, cases of acute sinusitis due to COVID-19 and even co-infections have been reported [1]. We want to discuss a case in Colombia where a patient with detected type 2 diabetes presented sinusitis and COVID-19. A 51-year-old man from Sincelejo, Sucre, consulted on May 23, 2020, with one day presenting general malaise and fever (38&#xa0;&#xb0;C), lumbar pain, frequent urination, polydipsia and hyperglycemia (366&#xa0;mg/dl). He denied cough, travel during the last two weeksan Physical examination revealed a blood pressure of 170/110&#xa0;mmHg, heart rate of 115 beats/minute, respiratory rate of 16 breaths/minute, and temperature of 36.6&#xa0;&#xb0;C. Neither lymphadenopathies nor cardiopulmonary disturbances were noted. A working diagnosis of febrile syndrome, ketoacidosis, and recent-onset type 2 diabetes, with uncontrolled hypertension, was contemplated at admission RT-PCR for SARS-CoV-2 was positive. A head CT Scan revealed left maxillary sinusitis with mucosal thickening of the maxillary Despite the sizeable SARS-CoV-2 pandemic, the number of reports of sinusitis in association with COVID-19 has been limited [2,3]. Sinusitis is more often diagnosed among immunocompromised patients, including diabetes of our patient. COVID-19, as a multisystemic condition. It may affect different anatomical areas, including the paranasal sinuses and the upper and lower respiratory mucosa. Although it is uncertain whether SARS-CoV-2 was the sole cause of the sinusitis in our patient or just a contributing factor, other reports suggest a significant involvement of the virus in the development of this condition, in addition to its role in worsening the clinical course of patients with chronic rhinosinusitis.</AbstractText><CopyrightInformation>&#xa9; 2022 Published by Elsevier Ltd.</CopyrightInformation></Abstract><AuthorList CompleteYN="Y"><Author ValidYN="Y"><LastName>Vergara-Hern&#xe1;ndez</LastName><ForeName>Juan Carlos</ForeName><Initials>JC</Initials><AffiliationInfo><Affiliation>Otorhinolaryngology Department, Santa Maria medical center, Sincelejo, Sucre, Colombia.</Affiliation></AffiliationInfo><AffiliationInfo><Affiliation>Otologist - Center for Otorhinolaryngology and Speech Therapy of La Sabana, Sincelejo, Sucre, Colombia.</Affiliation></AffiliationInfo></Author><Author ValidYN="Y"><LastName>Villamil-Gomez</LastName><ForeName>Wilmer E</ForeName><Initials>WE</Initials><AffiliationInfo><Affiliation>Infectious Diseases and Infection Control Research Group, Hospital Universitario de Sincelejo, Sincelejo, Sucre, Colombia.</Affiliation></AffiliationInfo><AffiliationInfo><Affiliation>Programa del Doctorado de Medicina Tropical, SUE Caribe, Universidad del Atl&#xe1;ntico, Barranquilla, Colombia.</Affiliation></AffiliationInfo><AffiliationInfo><Affiliation>Committee on Tropical Medicine, Zoonoses and Travel Medicine, Asociaci&#xf3;n Colombiana de Infectolog&#xed;a, Bogot&#xe1;, Colombia.</Affiliation></AffiliationInfo></Author><Author ValidYN="Y"><LastName>Collazos-Torres</LastName><ForeName>Luis Adolfo</ForeName><Initials>LA</Initials><AffiliationInfo><Affiliation>Infectious Diseases and Infection Control Research Group, Hospital Universitario de Sincelejo, Sincelejo, Sucre, Colombia.</Affiliation></AffiliationInfo></Author><Author ValidYN="Y"><LastName>Murillo-Moreno</LastName><ForeName>Mauricio</ForeName><Initials>M</Initials><AffiliationInfo><Affiliation>Infectious Diseases and Infection Control Research Group, Hospital Universitario de Sincelejo, Sincelejo, Sucre, Colombia.</Affiliation></AffiliationInfo></Author><Author ValidYN="Y"><LastName>Gonz&#xe1;lez-Bertel</LastName><ForeName>Laura Lucia</ForeName><Initials>LL</Initials><AffiliationInfo><Affiliation>Infectious Diseases and Infection Control Research Group, Hospital Universitario de Sincelejo, Sincelejo, Sucre, Colombia.</Affiliation></AffiliationInfo></Author><Author ValidYN="Y"><LastName>de-Jesus-Arrubla-Hoyos</LastName><ForeName>Wilson</ForeName><Initials>W</Initials><AffiliationInfo><Affiliation>Infectious Diseases and Infection Control Research Group, Hospital Universitario de Sincelejo, Sincelejo, Sucre, Colombia.</Affiliation></AffiliationInfo></Author><Author ValidYN="Y"><LastName>Cordero-Galaraga</LastName><ForeName>Alvaro Jose</ForeName><Initials>AJ</Initials><AffiliationInfo><Affiliation>Infectious Diseases and Infection Control Research Group, Hospital Universitario de Sincelejo, Sincelejo, Sucre, Colombia.</Affiliation></AffiliationInfo></Author><Author ValidYN="Y"><LastName>P&#xe9;rez-Coley</LastName><ForeName>Giselle</ForeName><Initials>G</Initials><AffiliationInfo><Affiliation>Infectious Diseases and Infection Control Research Group, Hospital Universitario de Sincelejo, Sincelejo, Sucre, Colombia.</Affiliation></AffiliationInfo></Author><Author ValidYN="Y"><LastName>L&#xf3;pez-Cartagena</LastName><ForeName>Neiris</ForeName><Initials>N</Initials><AffiliationInfo><Affiliation>Infectious Diseases and Infection Control Research Group, Hospital Universitario de Sincelejo, Sincelejo, Sucre, Colombia.</Affiliation></AffiliationInfo></Author><Author ValidYN="Y"><LastName>Palencia</LastName><ForeName>Yolima Esther Mercado</ForeName><Initials>YEM</Initials><AffiliationInfo><Affiliation>Infectious Diseases and Infection Control Research Group, Hospital Universitario de Sincelejo, Sincelejo, Sucre, Colombia.</Affiliation></AffiliationInfo></Author></AuthorList><Language>eng</Language><PublicationTypeList><PublicationType UI="D002363">Case Reports</PublicationType><PublicationType UI="D016428">Journal Article</PublicationType></PublicationTypeList><ArticleDate DateType="Electronic"><Year>2023</Year><Month>01</Month><Day>02</Day></ArticleDate></Article><MedlineJournalInfo><Country>Netherlands</Country><MedlineTA>IDCases</MedlineTA><NlmUniqueID>101634540</NlmUniqueID><ISSNLinking>2214-2509</ISSNLinking></MedlineJournalInfo><KeywordList Owner="NOTNLM"><Keyword MajorTopicYN="N">Acute sinusitis</Keyword><Keyword MajorTopicYN="N">COVID-19</Keyword><Keyword MajorTopicYN="N">Colombia</Keyword><Keyword MajorTopicYN="N">Type 2 Diabetes</Keyword></KeywordList></MedlineCitation><PubmedData><History><PubMedPubDate PubStatus="received"><Year>2022</Year><Month>6</Month><Day>20</Day></PubMedPubDate><PubMedPubDate PubStatus="revised"><Year>2022</Year><Month>12</Month><Day>10</Day></PubMedPubDate><PubMedPubDate PubStatus="accepted"><Year>2022</Year><Month>12</Month><Day>19</Day></PubMedPubDate><PubMedPubDate PubStatus="pubmed"><Year>2023</Year><Month>1</Month><Day>10</Day><Hour>6</Hour><Minute>0</Minute></PubMedPubDate><PubMedPubDate PubStatus="medline"><Year>2023</Year><Month>1</Month><Day>10</Day><Hour>6</Hour><Minute>1</Minute></PubMedPubDate><PubMedPubDate PubStatus="entrez"><Year>2023</Year><Month>1</Month><Day>9</Day><Hour>3</Hour><Minute>47</Minute></PubMedPubDate><PubMedPubDate PubStatus="pmc-release"><Year>2023</Year><Month>1</Month><Day>2</Day></PubMedPubDate></History><PublicationStatus>ppublish</PublicationStatus><ArticleIdList><ArticleId IdType="pubmed">36619214</ArticleId><ArticleId IdType="pmc">PMC9806927</ArticleId><ArticleId IdType="doi">10.1016/j.idcr.2022.e01664</ArticleId><ArticleId IdType="pii">S2214-2509(22)00292-X</ArticleId></ArticleIdList><ReferenceList><Reference><Citation>Lee S.W., Kim S.Y., Moon S.Y., et al. Estimating Covid-19 infection and severity risks in patients with, chronic rhinosinusitis: a Korean nationwide cohort study. J Allergy Clin Immunol: Pract. 2021;9(6):2262&#x2013;2271. e2262.</Citation><ArticleIdList><ArticleId IdType="pmc">PMC8079802</ArticleId><ArticleId IdType="pubmed">33931377</ArticleId></ArticleIdList></Reference><Reference><Citation>Alharthy A., Faqihi F., Karakitsos D. Sars-Cov-2 complicated by Sinusitis and Co-Infection with, HUman Metapneumovirus. R I Med J (2013) 2020;103(6):23&#x2013;24.</Citation><ArticleIdList><ArticleId IdType="pubmed">32752560</ArticleId></ArticleIdList></Reference><Reference><Citation>Ahmed O., Aladham Y., Mahmood S., Abdelnaby M.M. Complicated sinusitis with sphenopalatine artery thrombosis in a Covid-19 patient: a case report. J Surg Case Rep. 2021;2021(3):rjab010.</Citation><ArticleIdList><ArticleId IdType="pmc">PMC7947169</ArticleId><ArticleId IdType="pubmed">33732419</ArticleId></ArticleIdList></Reference><Reference><Citation>Rodriguez-Morales A.J., Cardona-Ospina J.A., Gutierrez-Ocampo E., et al. Clinical, laboratory and imaging features of Covid-19: a systematic review and meta-analysis. Travel Med Infect Dis. 2020;34</Citation><ArticleIdList><ArticleId IdType="pmc">PMC7102608</ArticleId><ArticleId IdType="pubmed">32179124</ArticleId></ArticleIdList></Reference><Reference><Citation>Ashour M.M., Abdelaziz T.T., Ashour D.M., Askoura A., Saleh M.I., Mahmoud M.S. Imaging spectrum of acute invasive fungal rhino-orbital-cerebral sinusitis in Covid-19 patients: a case series and a review of literature. J Neuroradiol = J De Neuroradiol. 2021</Citation><ArticleIdList><ArticleId IdType="pmc">PMC8168306</ArticleId><ArticleId IdType="pubmed">34087330</ArticleId></ArticleIdList></Reference><Reference><Citation>El-Kholy N.A., El-Fattah A.M.A., Khafagy Y.W. Invasive fungal sinusitis in post Covid-19 patients: a new clinical entity. Laryngoscope. 2021</Citation><ArticleIdList><ArticleId IdType="pmc">PMC8242424</ArticleId><ArticleId IdType="pubmed">34009676</ArticleId></ArticleIdList></Reference><Reference><Citation>Turbin R.E., Wawrzusin P.J., Sakla N.M., et al. Orbital cellulitis, sinusitis and intracranial abnormalities in two adolescents with Covid-19. Orbit. 2020;39(4):305&#x2013;310.</Citation><ArticleIdList><ArticleId IdType="pubmed">32419568</ArticleId></ArticleIdList></Reference><Reference><Citation>Rodriguez-Morales A.J., Sah R., Millan-O&#xf1;ate J., et al. Covid-19 associated mucormycosis: the urgent need to reconsider the indiscriminate use of immunosuppressive drugs. Ther Adv Infect Dis. 2021;8 20499361211027065.</Citation><ArticleIdList><ArticleId IdType="pmc">PMC8216396</ArticleId><ArticleId IdType="pubmed">34211710</ArticleId></ArticleIdList></Reference></ReferenceList></PubmedData></PubmedArticle></PubmedArticleSet>