{"drksId":"DRKS00029070","trialStatus":"UPDATED","registrationDrks":"2022-05-17","registrationType":"PROSPECTIVE","lastUpdate":"2023-11-08","sponsored":false,"url":null,"trialDescriptions":[{"idLocale":{"locale":"de"},"acronym":"ZANADIO-replication","title":"Anthropometrische und verhaltensbezogene Veränderungen mittels einer App-basierten multimodalen Behandlung für Patienten mit Adipositas","summary":"Adipositas stellt ein weltweites gesundheitliches Problem dar, welches Kinder und Erwachsene gleichermaßen betrifft. Effektive Behandlungsmaßnahmen sind immer noch selten und nur bedingt wirksam.\r\nDas Medizinprodukt zanadio, welches die aidhere GmbH als ein App-basiertes Behandlungsprogramm für Patient:innen mit Adipositas entwickelt hat soll in den Bereichen Verhalten, Ernährung und Bewegung eine Behandlung der Adipositas ermöglichen. Das Behandlungsprogramm dauert 12 Monate und bietet Nutzern eine ganzheitliche Behandlung, die auf eine gesunde und langfristige Änderung des Lebensstils ausgelegt ist. Ziel der Behandlung ist eine Gewichtsreduktion von mindestens 5% zum Ausgangsgewicht, eine verbesserte Lebensqualität und ein verbessertes Wohlbefinden. An der Studie können erwachsene Personen ab 18 Jahren mit einem BMI von 30 bis 45 kg/m2 teilnehmen.\r\nEs wird angenommen, dass das Behandlungsprogramm zu einem Gewichtsverlust von mindestens 5% zum Ausgangsgewicht führt, wie in einer vorherigen Studie bereits gezeigt werden konnte (DRKS00024415). Darüber hinaus wird angenommen, dass das Programm zu einer Reduktion des Taille-zu-Größe-Verhältnisses und zu Verbesserungen des Wohlbefindens sowie der adipositas-spezifischen Lebensqualität führt. Zudem wird davon ausgegangen, dass sich die Ernährungsgewohnheiten, die die Entstehung von Adipositas begünstigen, durch zanadio positiv verändern.","scientificSummary":"1) HINTERGRUND: Adipositas stellt ein weltweites gesundheitliches Problem dar, welches Kinder und Erwachsene gleichermaßen betrifft. Menschen mit Adipositas haben nicht nur ein erhöhtes Mortalitätsrisiko, sondern auch ein erhöhtes Risiko Adipositas-bedingte Begleiterkrankungen zu entwickeln. Dementsprechend ist eine rechtzeitige Behandlung von Adipositas dringend indiziert. Es hat sich gezeigt, dass sich bereits eine moderate Gewichtsreduktion positiv auf Komorbiditäten auswirkt und körperliche und psychische Begleiterkrankungen verbessert werden können. Trotz alledem sind effektive Behandlungsmaßnahmen immer noch selten und nur bedingt wirksam. Laut aktuellen Leitlinien und Empfehlungen sollte eine Behandlung von Adipositas eine graduelle Gewichtsreduktion durch ernährungs-, verhaltens- und bewegungstherapeutische Interventionen umfassen. Hierzu gibt es allerdings kaum flächendeckend verfügbare Programme.\r\n\r\n2) ZWECK: Diese Studie dient der Replikation der in der Evaluierungsstudie von zanadio erzielten Ergebnisse. Es soll an einer zweiten Stichprobe von Patient:innen mit erweitertem BMI-Bereich (BMI 30-45 kg/m2) untersucht werden, ob die Nutzung von zanadio zu einem signifikanten und klinisch relevanten Gewichtsverlust von mindestens 5% führt. \r\n\r\n3) ZIEL: Ziel der Behandlung ist es, eine Gewichtsreduktion von mindestens 5% zum Ausgangsgewicht, eine gesundheitsfördernde Änderung der Körperfettverteilung (d.h. Reduktion des viszeralen Bauchfetts), eine verbesserte adipositas-spezifische Lebensqualität und ein verbessertes Wohlbefinden innerhalb von 12 Monaten zu erreichen. Zudem wird davon ausgegangen, dass sich die Programmteilnahme positiv auf das Essverhalten auswirkt, welches Adipositas begünstigen kann. D.h.  mögliches maladaptives Ernährungsverhalten wie emotionales oder von äußeren Umständen gesteuertes Essverhalten soll sich verringern, während sich restriktives Essverhalten durch das Setting einer Intervention zur Gewichtsabnahme auch erhöhen könnte (vgl. The German version of the Dutch Eating Behaviour Questionnaire; DEBQ). \r\n\r\n4) PROGRAMM UND ABLAUF: Das Programm setzt sich aus validierten Inhalten und Interventionen aus den Bereichen Verhalten, Ernährung und Bewegung zusammen und soll so eine konservative, leitliniengerechte Behandlung der Adipositas ermöglichen. Das Behandlungsprogramm dauert 12 Monate und bietet Nutzern eine ganzheitliche Behandlung, die auf eine gesunde und langfristige Änderung des Lebensstils ausgelegt ist und sich an gültigen, wissenschaftlich anerkannten S3-Leitlinien orientiert.\r\nZu Beginn der Studie werden alle Studienteilnehmer per Telefon und Fragebogen auf Ein- und Ausschlusskriterien geprüft. Um zu vermeiden, dass mögliche nachgewiesene Effekte einer systematischen Verzerrung unterliegen, werden eingeschlossene Teilnehmer unter Beachtung ihres Alters und ihres BMI mittels der Methode der „Minimization“ (biased coin, 0.7 base probability) entweder der Interventions- oder der Kontrollgruppe zugeteilt.\r\nInterventionsgruppe (IG): Teilnehmer erhalten das App-basierte Behandlungsprogramm. Dies beinhaltet einen vollumfänglichen Zugang zur App mitsamt aller Inhalte für 12 Monate.\r\nKontrollgruppe (KG): Die Kontrollgruppe entspricht der durchschnittlichen Versorgungsrealität, in der Patient:innen mit Adipositas meist unbehandelt bleiben. Teilnehmer der Kontrollgruppe erhalten zunächst keinen Zugang zur App und keine weiteren Informationen oder Instruktionen hinsichtlich Interventionen zur Gewichtsveränderung. Teilnehmern der Kontrollgruppe wird kommuniziert, ihr Leben wie gewohnt fortzusetzen. Dies beinhaltet selbst- oder fremd-initiierte Versuche das Gewicht zu reduzieren oder individuelle Beschaffung von Informationsmaterial. Diese selbst- oder fremd-initiierten Diätversuche, die Nutzung von Hilfsmitteln, Veränderungen des Lebensstils, der Gesundheit oder der Lebenssituation werden zu den jeweiligen Messzeitpunkten erfasst. Weiterhin haben Teilnehmer in der Kontrollgruppe die Möglichkeit, nach 12 Monaten vollumfänglichen Zugang zum 12-monatigen Behandlungsprogramm zu bekommen. Über die aktive Studienphase hinweg werden zu 5 Messzeitpunkten im Intervall von 3 Monaten Daten erhoben. Für das Follow-Up werden zu weiteren 4 Zeitpunkten im Intervall von 6 Monaten Daten erhoben.\r\n\r\n5) STUDIENTEILNEHMER: Studienteilnehmer sind volljährige Patient:innen (> 18 Jahre) und einem BMI zwischen 30 und 45 kg/m2.\r\nAusschlusskriterien und Kontraindikationen stellen schwere körperliche Begleiterkrankungen, mangelnde körperliche Leistungsfähigkeit bzw. körperliche Einschränkungen, die eine mäßige eigenständigen physischen Aktivität nicht ermöglichen, akute unbehandelte oder instabile psychische Störungen, Zustand nach bariatrischer Operation und das Vorliegen sekundärer Adipositasformen, sowie das Cushing-Syndrom, Prader-Willi-Syndrom, Hypothyreose oder Hypogonadismus dar. Mangelnde körperliche Leistungsfähigkeit bzw. körperliche Einschränkungen beziehen sich hierbei auf die fehlende körperliche Fähigkeit Routine- bzw. Alltagshandlungen ohne Hilfe durchführen zu können. Akute unbehandelte oder instabile psychische Störungen beinhalten aktuell diagnostizierte psychische Erkrankung bzw. psychische Probleme, erhebliche Belastungen oder Einschränkungen im Alltag aufgrund einer psychischen Erkrankung bzw. psychischer Probleme, derzeit laufende therapeutische Behandlungen aufgrund einer psychischen Erkrankung oder psychischer Probleme, Medikamenteneinnahme (Psychopharmaka) aufgrund einer psychischen Erkrankung oder psychischer Probleme. Studienteilnehmer sollten weiterhin fließend Deutsch sprechen und schreiben können und im Besitz eines mobilen Endgerätes sein. Schwangere Probandinnen sowie Personen, die nicht in der Lage sind ihre informierte Einwilligung zu geben, werden außerdem von der Teilnahme ausgeschlossen.\r\n\r\n6) HYPOTHESEN:\r\n1) Die Teilnahme am zanadio Behandlungsprogramm führt zu einem Gewichtsverlust von mindestens 5% zum Ausgangsgewicht. \r\n2) Patient:innen, die am Behandlungsprogramm teilnehmen, weisen eine signifikant stärkere Gewichtsreduktion (in %) auf, als die Patient:innen, die nicht am Behandlungsprogramm teilnehmen.\r\n3) Die Teilnahme am zanadio Behandlungsprogramm führt zu einer signifikanten Reduktion des Taille-Größe-Verhältnisses. \r\n4) Patient:innen, die am Behandlungsprogramm teilnehmen, weisen eine signifikant stärkere Reduktion des Taille-Größe-Verhältnisses auf, als die Patient:innen, die nicht am Behandlungsprogramm teilnehmen.\r\n5) Die Teilnahme am zanadio Behandlungsprogramm führt zu einer signifikanten Verbesserung des Wohlbefindens.\r\n6) Patient:innen, die am Behandlungsprogramm teilnehmen, weisen eine signifikant stärkere Verbesserung des Wohlbefindens auf, als die Patient:innen, die nicht am Behandlungsprogramm teilnehmen.\r\n7) Die Teilnahme am zanadio Behandlungsprogramm führt zu einer signifikanten Verbesserung der Lebensqualität.\r\n8) Die Patient:innen,, die am Behandlungsprogramm teilnehmen, weisen eine signifikant stärkere Verbesserung der adipositas-spezifischen Lebensqualität auf, als die Patient:innen, die nicht am Behandlungsprogramm teilnehmen.\r\n9) Die Teilnahme am zanadio Behandlungsprogramm führt zu einer signifikanten Verringerung von emotionalem Essverhalten (DEBQ „emotional eating“).  \r\n10) Patient:innen, die am Behandlungsprogramm teilnehmen, weisen eine signifikant stärkere Verringerung des emotionalen Essverhaltens auf, als Patient:innen, die nicht am Behandlungsprogramm teilnehmen.\r\n11) Die Teilnahme am zanadio Behandlungsprogramm führt zu einer signifikanten Verringerung von Essverhalten, dass durch externe Einflussfaktoren gesteuert ist (DEBQ „external eating“).  \r\n12) Patient:innen die am Behandlungsprogramm teilnehmen, weisen eine signifikant stärkere Verringerung von Essverhalten, dass durch externe Einflussfaktoren gesteuert ist auf, als Patient:innen, die nicht am Behandlungsprogramm teilnehmen\r\n13) Die Teilnahme am zanadio Behandlungsprogramm führt zu einer signifikanten Erhöhung von restriktivem Essverhalten (DEBQ „restrictive eating“).  \r\n14) Patient:innen, die am Behandlungsprogramm teilnehmen, weisen eine signifikant stärkere Erhöhung von restriktivem Essverhalten auf, als Patient:innen, die nicht am Behandlungsprogramm teilnehmen."},{"idLocale":{"locale":"en"},"acronym":"ZANADIO-replication","title":"Anthropometric and behavioural changes after an app-based multimodal treatment for patients with obesity","summary":"Obesity is a worldwide health problem that affects children and adults alike. Effective treatment measures are still rare and only partially effective.\r\nThe medical product zanadio, developed by the company aidhere GmbH, is an app-based treatment program for patients with obesity. It is intended to provide treatment for obesity tackling the areas of behavior, nutrition and exercise. The treatment programme lasts 12 months and provides users with a multimodal treatment designed for a healthy and long-term lifestyle change. The main goal is to achieve a weight loss of at least 5% from baseline weight, improved quality of life, and improved well-being. Individuals with an age of at least 18 and a BMI of 30 to 45 kg/m2 are eligible to participate in the study. It is hypothesized that the treatment program will result in a weight loss of at least 5% from baseline weight, as demonstrated in a previous study (DRKS00024415). In addition, it is hypothesized that the program will lead to a reduction in waist-to-height ratio and improvements in well-being and obesity-specific quality of life.  Moreover, changes in mal-adaptive eating behaviours, i.e., emotional, restraint and external eating, that might influence weight and weight maintenance, will be analysed.","scientificSummary":"1) BACKGROUND: Obesity is a worldwide health problem that affects children and adults alike. Patients with obesity not only have an increased risk of mortality, but also an increased risk of developing obesity-related comorbidities. Accordingly, timely treatment of obesity is strongly indicated. Even moderate weight reduction has been shown to have a positive impact on comorbidities and to improve physical and psychological comorbidities. Despite all this, effective treatment interventions are still rare and only partially effective. According to current guidelines and recommendations, treatment of obesity should include gradual weight reduction through dietary, behavioral, and exercise interventions. However, there are few widely available programs for this purpose.\r\n\r\n2) PURPOSE: The purpose of this study is to replicate the results obtained in the zanadio evaluation study. It will be investigated in a second sample of patients with an extended BMI range (BMI 30-45 kg/m2) whether the use of zanadio leads to a significant and clinically relevant weight loss of at least 5%. \r\n\r\n3) OBJECTIVE: The goal of treatment is to achieve a weight loss of at least 5% from baseline weight, a health-promoting change in body fat distribution (i.e., reduction of visceral fat), improved obesity-specific quality of life, and improved well-being within 12 months. In addition, it is assumed that program participation positively affects mal-adaptive eating behavior, that has been associated with the development of obesity. The use of the program zanadio is assumed to reduce mal-adaptive eating behavior such as emotional eating or eating behavior controlled by external circumstances, while restrictive eating behavior could also be increased by the setting of an intervention for weight loss (cf. The German version of the Dutch Eating Behaviour Questionnaire; DEBQ).\r\n\r\n\r\n4) PROGRAM AND PROCEDURE: The program is composed of validated behavioral, nutritional, and exercise content and interventions designed to provide conservative, guideline-based treatment for obesity. The treatment program lasts 12 months and provides users with holistic treatment designed to promote healthy, long-term lifestyle changes and is guided by valid, scientifically accepted S3 guidelines.\r\nAt the beginning of the study, all study participants are screened for inclusion and exclusion criteria via telephone and questionnaire. In order to avoid that possible proven effects are subject to systematic bias, included participants will be allocated to either the intervention or the control group, taking into account their age and BMI, using the method of \"minimization\" (biased coin, 0.7 base probability).\r\nIntervention Group (IG): Participants will receive the app-based treatment program. This includes full access to the app including all content for 12 months.\r\nControl group (KG): The control group corresponds to the average care reality, in which patients with obesity usually go untreated. Participants in the control group will not initially receive access to the app or further information or instruction regarding weight change interventions. Participants in the control group are communicated to continue their lives as usual. This includes self- or peer-initiated attempts to reduce weight or individual acquisition of informational materials. These self-initiated or externally-initiated diet attempts, use of assistive devices, changes in lifestyle, health, or living situation are recorded at the respective measurement time points. Furthermore, participants in the control group will have the opportunity to gain full access to the 12-month treatment program after 12 months. Over the active study phase, data will be collected at 5 measurement time points at 3-month intervals. For follow-up, data will be collected at an additional 4 time points at 6 month intervals.\r\n\r\n5) STUDY PARTICIPANTS: Study participants will be adults (> 18 years) and BMI between 30 and 45 kg/m2.\r\nExclusion criteria and contraindications are severe concomitant physical diseases, poor physical performance or physical limitations that do not allow moderate independent physical activity, acute untreated or unstable mental disorders, condition after bariatric surgery and the presence of secondary forms of obesity, as well as Cushing's syndrome, Prader-Willi syndrome, hypothyroidism or hypogonadism. Lack of physical capacity or physical limitations here refer to the lack of physical ability to perform routine or everyday activities without assistance. Acute untreated or unstable mental disorders include currently diagnosed mental illness or mental problems, significant stress or limitations in daily life due to mental illness or mental problems, currently ongoing therapeutic treatments due to mental illness or mental problems, medication use (psychotropic drugs) due to mental illness or mental problems. Study participants should still be able to speak and write German fluently and be in possession of a mobile device. Pregnant subjects as well as subjects who are unable to give their informed consent will also be excluded from participation.\r\n\r\n6) HYPOTHESES:\r\n1) Participation in the zanadio treatment program will result in a weight loss of at least 5% from baseline weight. \r\n2) Patients who participate in the treatment program have significantly greater weight loss (%) than patients who do not participate in the treatment program.\r\n3) Participation in the zanadio treatment program results in a significant reduction in waist-to-height ratio. \r\n4) Patients who participate in the treatment program have a significantly greater reduction in waist-to-height-ratio than patients who do not participate in the treatment program.\r\n5) Participation in the zanadio treatment program leads to a significant improvement in well-being.\r\n6) Patients who participate in the treatment program show significantly greater improvement in well-being than patients who do not participate in the treatment program.\r\n7) Participation in the zanadio treatment program leads to a significant improvement in quality of life.\r\n8) Patients who participate in the treatment program show significantly greater improvement in obesity-specific quality of life than patients who do not participate in the treatment program.\r\n9) Participation in the zanadio treatment programme leads to a significant reduction in emotional eating behaviour (i.e., lower scores in DEBQ emotional eating subscale) from T0 to T4. \r\n10) The intervention group will show a greater decrease in emotional eating behaviour than the control group from T0 to T4.\r\n11) Participation in the zanadio treatment programme leads to a significant reduction in external eating behaviour (i.e., lower scores in DEBQ external eating subscale) from T0 to T4. \r\n12) The intervention group will show a greater decrease in external eating behaviour than the control group from T0 to T4.\r\n13)  Participation in the zanadio treatment programme leads to an increased restraint eating behaviour from T0 to T4. \r\n14) The intervention group will show a greater increase in restraint eating behaviour than the control group from T0 to T4."}],"observationalGroups":[{"idArm":{"arm":1,"locale":"de"},"comment":"Interventionsgruppe (IG): Teilnehmer erhalten das Interventionsprogramm zanadio (Medizinprodukt der Risikoklasse 1 gemäß MDD) über einen Zeitraum von 12 Monaten."},{"idArm":{"arm":1,"locale":"en"},"comment":"Intervention Group (IG): Participants receive the intervention program zanadio (medical device of risk class 1 according to MDD) over a period of 12 months."},{"idArm":{"arm":2,"locale":"de"},"comment":"Kontrollgruppe (KG): Teilnehmer der Kontrollgruppe erhalten zunächst keinen Zugang zum Interventionsprogramm zanadio und keine weiteren Informationen oder Instruktionen hinsichtlich Interventionen zur Gewichtsveränderung"},{"idArm":{"arm":2,"locale":"en"},"comment":"Control group (KG): Participants in the control group initially do not receive access to the zanadio intervention program and no further information or instructions regarding weight change interventions"}],"trialContacts":[{"idContactIdType":{"type":"PRIMARY_SPONSOR"},"otherType":null,"contact":{"streetAndNo":"ABC-Straße 21","city":"Hamburg","zip":"20354","country":"DE","email":"nora@aidhere.de","fax":null,"firstName":"Nora","lastName":"Mehl","phone":"04099997921","title":"Dr.","url":null,"affiliation":"aidhere GmbH"}},{"idContactIdType":{"type":"PUBLIC_QUERIES"},"otherType":null,"contact":{"streetAndNo":"Stephanstraße 1A","city":"Leipzig","zip":"04103","country":"DE","email":"rothl@cbs.mpg.de","fax":null,"firstName":"Lena","lastName":"Roth","phone":"040 285306251","title":null,"url":null,"affiliation":"Max-Planck Institut für Kognitions- und Neurowissenschaften"}},{"idContactIdType":{"type":"PRINCIPAL_COORDINATING_INVESTIGATOR"},"otherType":null,"contact":{"streetAndNo":"Stephanstraße 1A","city":"Leipzig","zip":"04103","country":"DE","email":"horstmann@cbs.mpg.de","fax":null,"firstName":"Annette","lastName":"Horstmann","phone":"034199402258","title":"Prof. Dr.","url":null,"affiliation":"Max-Planck- Institut für Kognitions- und Neurowissenschaften"}},{"idContactIdType":{"type":"SCIENTIFIC_QUERIES"},"otherType":null,"contact":{"streetAndNo":"Stephanstraße 1A","city":"Leipzig","zip":"04103","country":"DE","email":"horstmann@cbs.mpg.de","fax":null,"firstName":"Annette","lastName":"Horstmann","phone":"034199402258","title":"Prof. Dr.","url":null,"affiliation":"Max-Planck- Institut für Kognitions- und Neurowissenschaften"}}],"materialSupports":[{"contact":{"streetAndNo":"ABC-Straße 21","city":"Hamburg","zip":"20354","country":"DE","email":"info@aidhere.de","fax":null,"firstName":null,"lastName":null,"phone":"04099997921","title":null,"url":null,"affiliation":"aidhere GmbH"},"type":"COMMERCIAL"},{"contact":{"streetAndNo":"Stephanstraße 10A","city":"Leipzig","zip":"04103","country":"DE","email":"horstmann@cbs.mpg.de","fax":null,"firstName":null,"lastName":null,"phone":"034199402258","title":null,"url":null,"affiliation":"Max-Planck Institut für Kognitions- und Neurowissenschaften"},"type":"PUBLIC_FUNDING"}],"studyCharacteristic":{"type":"INTERVENTIONAL","allocation":"RANDOMIZED_CONTROLLED_TRIAL","assignment":"PARALLEL","blindingType":"OPEN","blindingWhoList":[],"controlTypes":[{"idControlType":{"controlType":"OTHER"}},{"idControlType":{"controlType":"RECEIVES_NO_TREATMENT"}}],"phase":"PHASE_IV","purpose":"TREATMENT","typeNonInterventional":null,"characteristicDescriptions":[{"idLocale":{"locale":"de"},"primaryOutcome":"Prozentuale Gewichtsveränderung nach 12 Monaten in Relation zum Ausgangsgewicht.","secondaryOutcome":"Reduktion der \r\n1) Körperfettverteilung operationalisiert als Taille-Größe-Verhältnis (Taillenumfang in cm dividiert durch Größe in cm, gemessen mit einem Maßband) sowie Verbesserungen des \r\n2) Wohlbefindens (WHO-5-Wohlbefindens-Index) und der \r\n3) adipositas-spezifischen Lebensqualität (IWQOL-Lite Fragebogen) nach 12 Monaten im Vergleich zum Ausgangswert zu Beginn der Studie; sowie\r\n4) eine gesundheitsförderliche Änderung des Essverhaltens (d.h. weniger emotional und external gesteuertes, aber restriktiveres Essverhalten nach 12 Monaten Programmteilnahme(DEBQ)).\r\n\r\nExplorative Endpunkte: \r\n1) Geschlechtsunterschiede bzgl. oben genannter Endpunkte, insb. des primären Endpunktes \r\n2) Follow-up: Änderungen o.g. Endpunkte nach 12 und 24 Monate nach Ende der aktiven Studienphase","typeOfHiddenAllocation":null,"typeOfSequenceGeneration":null},{"idLocale":{"locale":"en"},"primaryOutcome":"Percentage change in weight after 12 months in relation to baseline weight.","secondaryOutcome":"Reduction of \r\n1) body fat distribution operationalized as waist-to-height ratio (waist circumference in cm divided by height in cm, measured with a tape measure) and improvements in \r\n2) well-being (WHO-5 well-being index) and the \r\n3) obesity-specific quality of life (IWQOL-Lite questionnaire) at 12 months compared with baseline. \r\nMoreover, (4) a health-promoting change in eating behavior (, i.e., less emotionally and externally driven but likely more restrictive eating behavior after 12 months of program participation (DEBQ)).\r\n\r\nExploratory endpoints: \r\n1) Gender differences in regarding the aboveabove-mentioned  endpoints, especially in the primary endpoint. \r\n2) Follow-up: changes in the above-mentioned endpoints at 12 and 24 months after the active study phase has been completed.","typeOfHiddenAllocation":null,"typeOfSequenceGeneration":null}],"timing":null,"duration":null},"trialResults":{"ipdSharingPlan":false,"trialResultsDescriptions":[{"idLocale":{"locale":"de"},"ipdSharingPlanDescription":null,"briefSummaryOfResultsDescription":null},{"idLocale":{"locale":"en"},"ipdSharingPlanDescription":null,"briefSummaryOfResultsDescription":null}],"plannedPublication":null,"firstPublication":null,"firstResultPublication":null,"publications":[],"relatedDrksTrials":[{"drksId":"DRKS00024415","description":"Vorgängerstudie"}]},"secondaryIds":{"otherPrimaryRegisterId":null,"otherPrimaryRegisterName":null,"universalTrialNumber":null,"eudraCtNumber":null,"eudamedNumber":null,"noOtherIdentificationNumbersAvailable":false},"otherSecondaryIds":[{"value":"doi.org/10.17605/OSF.IO/HAV7Z","description":"OSF"}],"studiedHealthConditions":[{"type":"MAIN","catalog":"FREETEXT","code":null,"studiedHealthConditionDescriptions":[{"idLocale":{"locale":"de"},"comment":"E66.00 Adipositas durch übermäßige Kalorienzufuhr : Adipositas Grad I (WHO) bei Patienten von 18 Jahren und älter"},{"idLocale":{"locale":"en"},"comment":"E66.00 Obesity due to excess calories Grade 1 obesity (WHO) in patients aged 18 and over"}]},{"type":"OTHER","catalog":"FREETEXT","code":null,"studiedHealthConditionDescriptions":[{"idLocale":{"locale":"de"},"comment":"E66.01 Adipositas durch übermäßige Kalorienzufuhr : Adipositas Grad II (WHO) bei Patienten von 18 Jahren und älter"},{"idLocale":{"locale":"en"},"comment":"E66.01 Obesity due to excess calories Grade 2 obesity (WHO) in patients aged 18 and over"}]},{"type":"OTHER","catalog":"FREETEXT","code":null,"studiedHealthConditionDescriptions":[{"idLocale":{"locale":"de"},"comment":"E66.02 Adipositas durch übermäßige Kalorienzufuhr : Adipositas Grad III (WHO) bei Patienten von 18 Jahren und älter"},{"idLocale":{"locale":"en"},"comment":"E66.02 Obesity due to excess calories Grade 3 obesity (WHO) in patients aged 18 and over"}]}],"recruitment":{"institutes":[{"type":"OTHER","name":"Die Rekrutierung erfolgt über Posteraushänge in bis zu 12 Arztpraxen (Innere Medizin, Diabetologie, Endokrinologie) und Adipositaszentren verteilt über Deutschland sowie online.","city":"online"}],"countries":[{"idCountry":{"code":"DE"}}],"centricType":"MULTICENTRIC","gender":"ALL","minimumAge":{"amount":18,"unit":"YEARS"},"maximumAge":{"amount":null,"unit":"NO_MAX_AGE"},"totalParticipants":210,"plannedParticipants":200,"status":"DISCONTINIUED","recruitmentDescriptions":[{"idLocale":{"locale":"de"},"reasonDescription":"Erhebung eingestellt auf Grund von Insolvenz des Projektpartners.","exclusionCriteria":"1) schwere körperliche Begleiterkrankungen, mangelnde körperliche Leistungsfähigkeit, körperliche Einschränkungen die eine mäßige eigenständige physischen Aktivität nicht ermöglichen\r\n2) aktuell diagnostizierte psychische Erkrankung bzw. psychische Probleme, erhebliche Belastungen oder Einschränkungen im Alltag aufgrund einer psychischen Erkrankung bzw. psychischer Probleme, derzeit laufende psychotherapeutische Behandlungen, Medikamenteneinnahme (Psychopharamaka)\r\n3) Zustand nach bariatrischer Operation\r\n4) sekundäre Adipositasformen (Cushing-Syndrom, Prader-Willi-Syndrom, Hypothyreose oder Hypogonadismus)\r\n5) Schwangerschaft\r\n6) Personen, die nicht fähig sind ihre Einwilligung zu geben","inclusionCriteria":"1) volljährige Patient:innen mit Adipositas (m/w/d) \r\n2) BMI zwischen 30 und 45 kg/m2 3) fließendes Deutsch in Wort und Schrift\r\n4) Besitz eines mobilen Endgerätes"},{"idLocale":{"locale":"en"},"reasonDescription":"Data collection discontinued due to insolvency of project partner.","exclusionCriteria":"1) severe concomitant physical illnesses, lack of physical fitness, physical limitations that do not allow moderate independent physical activity.\r\n2) currently diagnosed mental illness or mental problems, significant stress or limitations in everyday life due to mental illness or mental problems, currently ongoing psychotherapeutic treatments, taking medication (psychopharamaceuticals)\r\n3) condition after bariatric surgery\r\n4) secondary forms of obesity (Cushing's syndrome, Prader-Willi syndrome, hypothyroidism or hypogonadism)\r\n5) pregnancy\r\n6) people who are not able to give their consent","inclusionCriteria":"1) patients of legal age with obesity (m/f/d) \r\n2) BMI between 30 and 45 kg/m2 3) fluent written and spoken German\r\n4) possession of a mobile device"}],"scheduledStartDate":"2022-05-19","scheduledCompletionDate":"2025-09-17","actualStartDate":"2022-05-23","actualCompletionDate":null,"healthyVolunteers":false},"ethicsCommittee":{"applicationDate":"2021-12-17","number":"511/20-ek","ethicVotes":[{"dateOfVote":"2022-01-06","vote":"APPROVED","type":"ETHICS_COMMITTEE","contact":{"streetAndNo":"Liebigstraße 18","city":"Leipzig","zip":"04103","country":"DE","email":"ethik@medizin.uni-leipzig.de","fax":"+49-341-9715499","firstName":null,"lastName":null,"phone":"+49-341-9715490","title":null,"url":"home.uni-leipzig.de/ethik","affiliation":"Geschäftsstelle der Ethik-Kommission an der Medizinischen Fakultät der Universität Leipzig c/o Zentrale Poststelle"}}]}}